pypanther/__init__.py
pypanther/backend/__init__.py
pypanther/backend/client.py
pypanther/backend/errors.py
pypanther/backend/graphql/bulk_upload_detections.graphql
pypanther/backend/graphql/bulk_upload_detections_status.graphql
pypanther/backend/graphql/bulk_upload_presigned_url.graphql
pypanther/backend/graphql/create_or_update_schema.graphql
pypanther/backend/graphql/list_schemas.graphql
pypanther/backend/public_api_client.py
pypanther/backend/util.py
pypanther/base.py
pypanther/cache.py
pypanther/cli_output.py
pypanther/command/standard_args.py
pypanther/config.py
pypanther/constants.py
pypanther/custom_logging.py
pypanther/data_models/__init__.py
pypanther/data_models/asana.py
pypanther/data_models/atlassian.py
pypanther/data_models/aws_alb.py
pypanther/data_models/aws_cloudtrail.py
pypanther/data_models/aws_eks.py
pypanther/data_models/aws_s3.py
pypanther/data_models/aws_vpcdns.py
pypanther/data_models/aws_vpcflow.py
pypanther/data_models/azure_signin.py
pypanther/data_models/box.py
pypanther/data_models/cisco_umbrella.py
pypanther/data_models/cloudflare_firewall.py
pypanther/data_models/cloudflare_httpreq.py
pypanther/data_models/crowdstrike_fdr.py
pypanther/data_models/gcp.py
pypanther/data_models/github.py
pypanther/data_models/gsuite.py
pypanther/data_models/notion.py
pypanther/data_models/ocsf_dnsactivity.py
pypanther/data_models/ocsf_networkactivity.py
pypanther/data_models/okta.py
pypanther/data_models/onelogin.py
pypanther/data_models/onepassword_itemusage.py
pypanther/data_models/onepassword_signinattempt.py
pypanther/data_models/panther_audit.py
pypanther/data_models/slack_accesslogs.py
pypanther/data_models/slack_auditlogs.py
pypanther/data_models/slack_integrationlogs.py
pypanther/data_models/zendesk.py
pypanther/data_models/zoom_activity.py
pypanther/data_models/zoom_operation.py
pypanther/data_models_v2.py
pypanther/display.py
pypanther/generate.py
pypanther/get.py
pypanther/get_rule.py
pypanther/helpers/__init__.py
pypanther/helpers/asana.py
pypanther-0.1.1a60.dist-info/LICENSE.txt
pypanther-0.1.1a60.dist-info/METADATA
pypanther-0.1.1a60.dist-info/WHEEL
pypanther-0.1.1a60.dist-info/entry_points.txt
pypanther-0.1.1a60.dist-info/RECORD
