Metadata-Version: 2.1
Name: pypanther
Version: 0.1.1a60
Summary: 
License: Apache-2.0
Keywords: Security,CLI
Author: Panther Labs Inc
Author-email: pypi@runpanther.io
Requires-Python: ==3.11.*
Classifier: License :: OSI Approved :: Apache Software License
Classifier: Operating System :: OS Independent
Classifier: Programming Language :: Python :: 3
Classifier: Programming Language :: Python :: 3.11
Requires-Dist: aiohttp (>=3.9.5,<=3.11.6)
Requires-Dist: ast-comments (>=1.2.2,<2.0.0)
Requires-Dist: boto3 (>=1.34.99,<2.0.0)
Requires-Dist: colorama (>=0.4.6,<0.5.0)
Requires-Dist: dynaconf (>=3.2.5,<4.0.0)
Requires-Dist: gitpython (>=3.1.43,<4.0.0)
Requires-Dist: gql (>=3.5.0,<4.0.0)
Requires-Dist: jsonpath-ng (>=1.6.1,<2.0.0)
Requires-Dist: panther-core (>=0.11.2,<1.0)
Requires-Dist: panther-detection-helpers (>=0.4.0,<0.5.0)
Requires-Dist: policyuniverse (>=1.5.1.20231109,<2.0.0.0)
Requires-Dist: prettytable (>=3.10.0,<4.0.0)
Requires-Dist: pycountry (>=24.6.1,<25.0.0)
Requires-Dist: pydantic (>=2.7.1,<3.0.0)
Requires-Dist: ruamel-yaml (>=0.18.6,<0.19.0)
Requires-Dist: ruff (>=0.4.4,<0.5.0)
Requires-Dist: types-requests (>=2.32.0.20241016,<3.0.0.0)
